[
  {
    "elementType": "geometry",
    "stylers": [
      {
        "color": "#212121"
      }
    ]
  },
  {
    "elementType": "labels",
    "stylers": [
      {
        "visibility": "on"
      }
    ]
  },
  {
    "elementType": "labels.icon",
    "stylers": [
      {
        "visibility": "off"
      }
    ]
  },
  {
    "elementType": "labels.text",
    "stylers": [
      {
        "visibility": "on"
      }
    ]
  },
  {
    "elementType": "labels.text.fill",
    "stylers": [
      {
        "color": "#757575"
      }
    ]
  },
  {
    "elementType": "labels.text.stroke",
    "stylers": [
      {
        "color": "#212121"
      }
    ]
  },
  {
    "featureType": "administrative",
    "elementType": "geometry",
    "stylers": [
      {
        "color": "#757575"
      }
    ]
  },
  {
    "featureType": "administrative",
    "elementType": "labels",
    "stylers": [
      {
        "color": "#dbdbdb"
      }
    ]
  },
  {
    "featureType": "administrative",
    "elementType": "labels.text.stroke",
    "stylers": [
      {
        "color": "#2c2c2c"
      }
    ]
  },
  {
    "featureType": "administrative.country",
    "elementType": "geometry.stroke",
    "stylers": [
      {
        "color": "#38abb1"
      },
      {
        "visibility": "on"
      }
    ]
  },
  {
    "featureType": "administrative.country",
    "elementType": "labels.text.fill",
    "stylers": [
      {
        "color": "#ffffff"
      },
      {
        "lightness": 45
      }
    ]
  },
  {
    "featureType": "administrative.province",
    "elementType": "labels.text",
    "stylers": [
      {
        "color": "#d6d6d6"
      },
      {
        "lightness": -15
      }
    ]
  },
  {
    "featureType": "administrative.province",
    "elementType": "labels.text.stroke",
    "stylers": [
      {
        "color": "#2a2a2a"
      }
    ]
  },
  {
    "featureType": "poi",
    "elementType": "labels.icon",
    "stylers": [
      {
        "visibility": "on"
      }
    ]
  },
  {
    "featureType": "poi",
    "elementType": "labels.text",
    "stylers": [
      {
        "visibility": "on"
      }
    ]
  },
  {
    "featureType": "poi",
    "elementType": "labels.text.fill",
    "stylers": [
      {
        "color": "#757575"
      }
    ]
  },
  {
    "featureType": "poi.park",
    "elementType": "geometry",
    "stylers": [
      {
        "color": "#181818"
      }
    ]
  },
  {
    "featureType": "poi.park",
    "elementType": "labels.text",
    "stylers": [
      {
        "color": "#d3d3d3"
      }
    ]
  },
  {
    "featureType": "poi.park",
    "elementType": "labels.text.stroke",
    "stylers": [
      {
        "color": "#2c2c2c"
      }
    ]
  },
  {
    "featureType": "road",
    "elementType": "geometry.fill",
    "stylers": [
      {
        "color": "#2c2c2c"
      }
    ]
  },
  {
    "featureType": "road",
    "elementType": "labels.text.fill",
    "stylers": [
      {
        "color": "#8a8a8a"
      }
    ]
  },
  {
    "featureType": "road.arterial",
    "elementType": "geometry",
    "stylers": [
      {
        "color": "#373737"
      }
    ]
  },
  {
    "featureType": "road.highway",
    "elementType": "geometry",
    "stylers": [
      {
        "color": "#b65718"
      }
    ]
  },
  {
    "featureType": "road.highway",
    "elementType": "labels.icon",
    "stylers": [
      {
        "visibility": "on"
      }
    ]
  },
  {
    "featureType": "road.highway.controlled_access",
    "elementType": "geometry",
    "stylers": [
      {
        "color": "#4e4e4e"
      }
    ]
  },
  {
    "featureType": "road.local",
    "elementType": "labels.text.fill",
    "stylers": [
      {
        "color": "#616161"
      }
    ]
  },
  {
    "featureType": "transit",
    "elementType": "labels.text.fill",
    "stylers": [
      {
        "color": "#757575"
      }
    ]
  },
  {
    "featureType": "water",
    "elementType": "geometry",
    "stylers": [
      {
        "color": "#3e6b99"
      }
    ]
  },
  {
    "featureType": "water",
    "elementType": "labels",
    "stylers": [
      {
        "color": "#e8e8e8"
      }
    ]
  }
]